web_prink/__init__.py
web_prink/__main__.py
web_prink/__version__.py
web_prink/main.py
web_prink/pdf_logic.py
web_prink/scan_logic.py
web_prink/sup.py
web_prink-0.4.0.dist-info/LICENSE
web_prink-0.4.0.dist-info/METADATA
web_prink-0.4.0.dist-info/WHEEL
web_prink-0.4.0.dist-info/entry_points.txt
web_prink-0.4.0.dist-info/top_level.txt
web_prink-0.4.0.dist-info/RECORD
