Metadata-Version: 2.1
Name: web_prink
Version: 0.4.0
License-File: LICENSE
Requires-Dist: gradio
Requires-Dist: pypdf
